chromathicity/__init__.py
chromathicity/chromadapt.py
chromathicity/convert.py
chromathicity/error.py
chromathicity/illuminant.py
chromathicity/manage.py
chromathicity/math.py
chromathicity/mixin.py
chromathicity/observer.py
chromathicity/rgbspec.py
chromathicity/space_names.py
chromathicity/spaces.py
chromathicity/util.py
chromathicity-0.3.0.dist-info/DESCRIPTION.rst
chromathicity-0.3.0.dist-info/METADATA
chromathicity-0.3.0.dist-info/RECORD
chromathicity-0.3.0.dist-info/WHEEL
chromathicity-0.3.0.dist-info/metadata.json
chromathicity-0.3.0.dist-info/top_level.txt
