Metadata-Version: 2.0
Name: chromathicity
Version: 0.3.0
Summary: Extensible color conversions
Home-page: https://hoogamaphone.github.io/chromathicity/
Author: Christopher Hoogeboom
Author-email: chris.hoogeboom@gmail.com
License: BSD
Keywords: color color-space cielab ciexyz math conversion convert
Platform: UNKNOWN
Classifier: Development Status :: 4 - Beta
Classifier: Intended Audience :: Developers
Classifier: License :: OSI Approved :: BSD License
Classifier: Natural Language :: English
Classifier: Operating System :: OS Independent
Classifier: Programming Language :: Python
Classifier: Topic :: Scientific/Engineering :: Mathematics
Classifier: Topic :: Software Development :: Libraries :: Python Modules
Classifier: Programming Language :: Python :: 3.6
Requires-Dist: bidict
Requires-Dist: networkx
Requires-Dist: scipy
